README.md
setup.py
hakuna_matata/__init__.py
hakuna_matata.egg-info/PKG-INFO
hakuna_matata.egg-info/SOURCES.txt
hakuna_matata.egg-info/dependency_links.txt
hakuna_matata.egg-info/entry_points.txt
hakuna_matata.egg-info/top_level.txt
hakuna_matata/agent/__init__.py
hakuna_matata/agent/asp.py
hakuna_matata/agent/mode.py
hakuna_matata/agent/perfect.py
hakuna_matata/agent/proxy.py
hakuna_matata/asp/__init__.py
hakuna_matata/asp/answer.py
hakuna_matata/asp/lite.py
hakuna_matata/cli/__init__.py
hakuna_matata/cli/__main__.py
hakuna_matata/common/__init__.py
hakuna_matata/common/action.py
hakuna_matata/common/grid.py
hakuna_matata/common/location.py
hakuna_matata/common/orientation.py
hakuna_matata/common/percept.py
hakuna_matata/simulator/__init__.py
hakuna_matata/simulator/world.py
hakuna_matata/util/__init__.py