Metadata-Version: 2.1
Name: hakuna-matata
Version: 0.0.2
Summary: A logic-based agent that plays Hunt the Wumpus
Home-page: https://github.com/lorenzleutgeb/ils
Author: Lorenz Leutgeb
Author-email: lorenz@leutgeb.xyz
License: MIT
Platform: UNKNOWN
Classifier: Programming Language :: Python :: 3
Classifier: License :: OSI Approved :: MIT License
Classifier: Operating System :: POSIX :: Linux
Classifier: Topic :: Scientific/Engineering :: Artificial Intelligence
Classifier: Topic :: Education
